wikiextractor/WikiExtractor.py
wikiextractor/__init__.py
wikiextractor/cirrus-extract.py
wikiextractor/clean.py
wikiextractor/extract.py
wikiextractor/extractPage.py
wikiextractorKR-1.0.0.dist-info/LICENSE
wikiextractorKR-1.0.0.dist-info/METADATA
wikiextractorKR-1.0.0.dist-info/WHEEL
wikiextractorKR-1.0.0.dist-info/entry_points.txt
wikiextractorKR-1.0.0.dist-info/top_level.txt
wikiextractorKR-1.0.0.dist-info/RECORD
