Metadata-Version: 2.1
Name: wikiextractorKR
Version: 1.0.0
Summary: A tool for extracting plain text from Wikipedia dumps
Home-page: https://github.com/choiyonugwon/modified_wikiextractor
Author: choi yong won
Author-email: choiyonugwon@gmail.com
License: GNU Affero General Public License
Classifier: Development Status :: 5 - Production/Stable
Classifier: Intended Audience :: Developers
Classifier: Topic :: Text Processing :: Linguistic
Classifier: License :: OSI Approved :: GNU Affero General Public License v3 or later (AGPLv3+)
Classifier: Programming Language :: Python :: 3
Requires-Python: >=3.6
License-File: LICENSE
